weather.py
amapote_moni_mcp_server_xyt-0.1.9.dist-info/METADATA
amapote_moni_mcp_server_xyt-0.1.9.dist-info/WHEEL
amapote_moni_mcp_server_xyt-0.1.9.dist-info/entry_points.txt
amapote_moni_mcp_server_xyt-0.1.9.dist-info/top_level.txt
amapote_moni_mcp_server_xyt-0.1.9.dist-info/RECORD
